jdAppdataEdit/AboutWindow.py
jdAppdataEdit/AboutWindow.ui
jdAppdataEdit/AdvancedWidget.py
jdAppdataEdit/AdvancedWidget.ui
jdAppdataEdit/ArtifactWindow.py
jdAppdataEdit/ArtifactWindow.ui
jdAppdataEdit/DescriptionWidget.py
jdAppdataEdit/DescriptionWidget.ui
jdAppdataEdit/Enviroment.py
jdAppdataEdit/Functions.py
jdAppdataEdit/Icon.svg
jdAppdataEdit/MainWindow.py
jdAppdataEdit/MainWindow.ui
jdAppdataEdit/ManageTemplatesWindow.py
jdAppdataEdit/ManageTemplatesWindow.ui
jdAppdataEdit/OarsWidget.py
jdAppdataEdit/OarsWidget.ui
jdAppdataEdit/RelationsWidget.py
jdAppdataEdit/RelationsWidget.ui
jdAppdataEdit/ReleaseImporter.py
jdAppdataEdit/ReleasesWindow.py
jdAppdataEdit/ReleasesWindow.ui
jdAppdataEdit/ScreenshotWindow.py
jdAppdataEdit/ScreenshotWindow.ui
jdAppdataEdit/Settings.py
jdAppdataEdit/SettingsWindow.py
jdAppdataEdit/SettingsWindow.ui
jdAppdataEdit/TranslateWindow.py
jdAppdataEdit/TranslateWindow.ui
jdAppdataEdit/ValidateWindow.py
jdAppdataEdit/ValidateWindow.ui
jdAppdataEdit/ViewXMLWindow.py
jdAppdataEdit/ViewXMLWindow.ui
jdAppdataEdit/__init__.py
jdAppdataEdit/__main__.py
jdAppdataEdit/version.txt
jdAppdataEdit/data/categories.txt
jdAppdataEdit/data/langcodes.txt
jdAppdataEdit/data/metadata_licenses.json
jdAppdataEdit/data/platform.json
jdAppdataEdit/data/project_licenses.json
jdAppdataEdit/i18n/jdAppdataEdit_de.qm
jdAppdataEdit/i18n/jdAppdataEdit_nl.qm
jdAppdataEdit-5.1.dist-info/LICENSE
jdAppdataEdit-5.1.dist-info/METADATA
jdAppdataEdit-5.1.dist-info/WHEEL
jdAppdataEdit-5.1.dist-info/entry_points.txt
jdAppdataEdit-5.1.dist-info/top_level.txt
jdAppdataEdit-5.1.dist-info/RECORD
