Metadata-Version: 2.1
Name: jdAppdataEdit
Version: 5.1
Summary: A graphical Program to create and edit Appdata files
Home-page: https://gitlab.com/JakobDev/jdAppdataEdit
Download-URL: https://gitlab.com/JakobDev/jdAppdataEdit/-/releases
Author: JakobDev
Author-email: jakobdev@gmx.de
License: GPL v3
Project-URL: Issue tracker, https://gitlab.com/JakobDev/jdAppdataEdit/-/issues
Keywords: JakobDev,PyQt6
Classifier: Development Status :: 5 - Production/Stable
Classifier: Intended Audience :: Developers
Classifier: Intended Audience :: End Users/Desktop
Classifier: Environment :: Other Environment
Classifier: Environment :: X11 Applications :: Qt
Classifier: License :: OSI Approved :: GNU General Public License v3 (GPLv3)
Classifier: Natural Language :: English
Classifier: Natural Language :: German
Classifier: Natural Language :: Dutch
Classifier: Topic :: Text Editors
Classifier: Operating System :: OS Independent
Classifier: Operating System :: POSIX
Classifier: Operating System :: POSIX :: BSD
Classifier: Operating System :: POSIX :: Linux
Classifier: Operating System :: MacOS :: MacOS X
Classifier: Operating System :: Microsoft :: Windows
Classifier: Programming Language :: Python :: 3
Classifier: Programming Language :: Python :: 3.9
Classifier: Programming Language :: Python :: 3.10
Classifier: Programming Language :: Python :: 3 :: Only
Classifier: Programming Language :: Python :: Implementation :: CPython
Requires-Python: >=3.9
License-File: LICENSE
Requires-Dist: PyQt6
Requires-Dist: requests
Requires-Dist: lxml
Provides-Extra: import_.desktop_files
Requires-Dist: desktop-entry-lib ; extra == 'import_.desktop_files'
Provides-Extra: sort_releases
Requires-Dist: packaging ; extra == 'sort_releases'
